sqlitehint/__init__.py
sqlitehint/dbapi.py
sqlitehint/dbapi.pyi
SQLiteHint-1.0.19.dist-info/LICENSE.txt
SQLiteHint-1.0.19.dist-info/METADATA
SQLiteHint-1.0.19.dist-info/WHEEL
SQLiteHint-1.0.19.dist-info/top_level.txt
SQLiteHint-1.0.19.dist-info/RECORD
