Metadata-Version: 2.1
Name: SQLiteHint
Version: 1.0.19
Summary: Have a easier SQLite with helpful methods and readable syntax with sqlitehint.
Home-page: https://github.com/awolverp/sqlitehint/
Author: awolverp
Author-email: awolverp@gmail.com
Project-URL: Github, https://github.com/awolverp/sqlitehint/
Project-URL: Bug Tracker, https://github.com/awolverp/sqlitehint/issues/new
Classifier: Programming Language :: Python :: 3
Classifier: License :: OSI Approved :: MIT License
Classifier: Operating System :: OS Independent
License-File: LICENSE.txt
